LICENSE.txt
README.md
setup.cfg
setup.py
t4json/__init__.py
t4json/t4json.py
t4json.egg-info/PKG-INFO
t4json.egg-info/SOURCES.txt
t4json.egg-info/dependency_links.txt
t4json.egg-info/requires.txt
t4json.egg-info/top_level.txt