Metadata-Version: 2.1
Name: t4json
Version: 1.4.2
Summary: Tools to work with JSON data easily and quickly.
Home-page: https://cybergeek1943.github.io/t4json/
Author: Isaac Wolford
Author-email: cybergeek.1943@gmail.com
License: MIT
Download-URL: https://github.com/cybergeek1943/t4json/archive/refs/tags/v1.4.2.tar.gz
Keywords: json,tool,tools,data,structures,flattening,t4json,flatten,nested
Platform: UNKNOWN
Classifier: Development Status :: 5 - Production/Stable
Classifier: Intended Audience :: Developers
Classifier: Topic :: Software Development :: Build Tools
Classifier: License :: OSI Approved :: MIT License
Classifier: Programming Language :: Python :: 3.6
Classifier: Programming Language :: Python :: 3.7
Classifier: Programming Language :: Python :: 3.8
Classifier: Programming Language :: Python :: 3.9
Classifier: Programming Language :: Python :: 3.10
License-File: LICENSE.txt
